hadroncomb/__init__.py
hadroncomb/__main__.py
hadroncomb/version.py
hadroncomb-1.0.0.dist-info/METADATA
hadroncomb-1.0.0.dist-info/WHEEL
hadroncomb-1.0.0.dist-info/top_level.txt
hadroncomb-1.0.0.dist-info/RECORD
