Metadata-Version: 2.1
Name: hadroncomb
Version: 1.0.0
Summary: Combination tool for hadronic decays in LHCb
Home-page: https://gitlab.cern.ch/jagoodin/hadroncomb
Author: Jamie Gooding
Author-email: jamie.gooding@cern.ch
License: GNU General Public License v3 (GPLv3)
Project-URL: Bug Tracker, https://gitlab.cern.ch/jagoodin/hadroncomb/issues
Classifier: License :: OSI Approved :: GNU General Public License v3 (GPLv3)
Classifier: Programming Language :: Python :: 3
Classifier: Operating System :: OS Independent
Requires-Python: >=3.6
Requires-Dist: numpy
